ig_gds_utilities/__init__.py
ig_gds_utilities/ig_utilities.py
ig_gds_utilities-0.1.8.4.data/data/config_utilities_EXAMPLE.cfg
ig_gds_utilities-0.1.8.4.dist-info/LICENSE
ig_gds_utilities-0.1.8.4.dist-info/METADATA
ig_gds_utilities-0.1.8.4.dist-info/WHEEL
ig_gds_utilities-0.1.8.4.dist-info/top_level.txt
ig_gds_utilities-0.1.8.4.dist-info/RECORD
