Metadata-Version: 2.1
Name: ig-gds-utilities
Version: 0.1.8.4
Summary: Python library to be used by differente GDS services
Home-page: https://github.com/awacero/ig_gds_utilities
Author: Wilson Acero
Author-email: acerowilson@gmail.com
Classifier: Programming Language :: Python :: 3
Classifier: License :: OSI Approved :: MIT License
Classifier: Operating System :: OS Independent
License-File: LICENSE
Requires-Dist: requests >=2.22.0
